{
  "cipher": "PRESENT-80",
  "claim_scope": "seed6 PRESENT r3 selected-eight-output SPN-ResCNN hybrid discovery; not r4 evidence, full-ciphertext recovery, sample classification, or SOTA",
  "config": {
    "batch_size": 250,
    "data_chunk_rows": 4096,
    "device": "cuda",
    "epochs": 100,
    "learning_rate": 0.001,
    "lstm_hidden_dim": 300,
    "lstm_layers": 6,
    "minimum_accuracy_margin": 0.005,
    "minimum_candidate_anchor_gain": 0.01,
    "minimum_candidate_mean_auc": 0.55,
    "minimum_mean_shuffle_margin": 0.03,
    "minimum_mean_topology_margin": 0.02,
    "minimum_passed_bits": 4,
    "minimum_per_bit_anchor_gain": 0.005,
    "minimum_per_bit_auc": 0.55,
    "minimum_per_bit_control_margin": 0.015,
    "mlp_hidden_dim": 1936,
    "mode": "spn_rescnn_hybrid",
    "rescnn_blocks": 10,
    "rescnn_channels": 252,
    "rounds": 3,
    "run_id": "i2_output_prediction_opc1_present_r3_spn_rescnn_hybrid_key6_gpu0_20260722",
    "seed": 6,
    "selected_msb_indices": [
      0,
      2,
      8,
      10,
      32,
      34,
      40,
      42
    ],
    "test_rows": 65536,
    "train_rows": 131072
  },
  "experiment": "opc1_present_r3_selected8_spn_rescnn_hybrid",
  "input": "64 MSB-first plaintext bits",
  "key_protocol": "seventh independent fixed unknown key; disjoint plaintext train/test",
  "mode": "spn_rescnn_hybrid",
  "opb1_gate_decision": "innovation2_topology_bottleneck_not_attributed",
  "parameter_counts": {
    "rescnn": 3955904,
    "spn_rescnn_exact_p": 3955904,
    "spn_rescnn_wrong_p": 3955904
  },
  "run_id": "i2_output_prediction_opc1_present_r3_spn_rescnn_hybrid_key6_gpu0_20260722",
  "sample_classification": false,
  "secret_key_hex": "d0673326c1b72ab3eb5f",
  "selected_msb_indices": [
    0,
    2,
    8,
    10,
    32,
    34,
    40,
    42
  ],
  "target": "eight preregistered MSB-first true ciphertext bits",
  "task": "innovation2_output_prediction"
}
